app/__init__.py
entree/__init__.py
entree/utils.py
entree/projects/__init__.py
entree/projects/base.py
entree/projects/flask.py
entree/projects/flask_large.py
entree/projects/html5.py
entree/projects/python.py
entree/projects/sqlalchemy.py
entree/projects/templates/common/.gitignore
entree/projects/templates/common/License.md
entree/projects/templates/common/README.md
entree/projects/templates/common/requirements.txt
entree/projects/templates/html5/index.html
entree/projects/templates/html5/static/css/style.css
entree/projects/templates/html5/static/js/app.js
entree/projects/templates/python/.gitignore
entree/projects/templates/python/License.md
entree/projects/templates/python/README.md
entree/projects/templates/python/requirements.txt
entree/projects/templates/python/setup_py.template
entree/projects/templates/python/src/__init___py.template
entree/projects/templates/python/tests/unittest_py.template
entree/projects/templates/python-flask/.gitignore
entree/projects/templates/python-flask/License.md
entree/projects/templates/python-flask/README.md
entree/projects/templates/python-flask/app_py.template
entree/projects/templates/python-flask/requirements.txt
entree/projects/templates/python-flask/static/css/style.css
entree/projects/templates/python-flask/static/js/app.js
entree/projects/templates/python-flask/templates/index.html
entree/projects/templates/python-flask-large/.gitignore
entree/projects/templates/python-flask-large/License.md
entree/projects/templates/python-flask-large/README.md
entree/projects/templates/python-flask-large/requirements.txt
entree/projects/templates/python-flask-large/setup_py.template
entree/projects/templates/python-flask-large/src/__init___py.template
entree/projects/templates/python-flask-large/src/models_py.template
entree/projects/templates/python-flask-large/src/views_py.template
entree/projects/templates/python-flask-large/src/static/css/style.css
entree/projects/templates/python-flask-large/src/static/js/app.js
entree-2.4.2.dist-info/METADATA
entree-2.4.2.dist-info/WHEEL
entree-2.4.2.dist-info/entry_points.txt
entree-2.4.2.dist-info/top_level.txt
entree-2.4.2.dist-info/RECORD
