Metadata-Version: 2.4
Name: entree
Version: 2.4.2
Summary: Tool to create skeleton files to start a programming project
Home-page: http://frenetic.be/
Download-URL: https://github.com/frenetic-be/entree/archive/2.4.2.tar.gz
Author: Julien Spronck
Author-email: github@frenetic.be
License: MIT
Keywords: software development productivity skeleton starter
Classifier: Development Status :: 5 - Production/Stable
Classifier: Intended Audience :: Developers
Classifier: Topic :: Software Development
Classifier: Topic :: Software Development :: Code Generators
Classifier: Topic :: Utilities
Classifier: License :: OSI Approved :: MIT License
Classifier: Programming Language :: Python :: 3.12
Requires-Dist: certifi==2025.1.31
Requires-Dist: chardet==5.2.0
Requires-Dist: click==8.1.8
Requires-Dist: Flask==3.1.0
Requires-Dist: gunicorn==23.0.0
Requires-Dist: idna==3.10
Requires-Dist: itsdangerous==2.2.0
Requires-Dist: Jinja2==3.1.6
Requires-Dist: MarkupSafe==3.0.2
Requires-Dist: requests==2.32.3
Requires-Dist: urllib3==2.3.0
Requires-Dist: Werkzeug==3.1.3
Dynamic: author
Dynamic: author-email
Dynamic: classifier
Dynamic: description
Dynamic: download-url
Dynamic: home-page
Dynamic: keywords
Dynamic: license
Dynamic: requires-dist
Dynamic: summary
